{
  "resources": [
    {
      "title": "Blueprint Test Image 1",
      "link": "https://twitter.com/kendalmintcode",
      "imageUrl": "https://placeimg.com/800/600/any"
    },
    {
      "title": "Blueprint Test Image 2",
      "link": "https://ark-labs.co.uk",
      "imageUrl": "https://placeimg.com/800/600/animals"
    },
    {
      "title": "Blueprint Test Image 3",
      "link": "https://twitter.com/kendalmintcode",
      "imageUrl": "https://placeimg.com/800/600/architecture"
    },
    {
      "title": "Blueprint Test Image 4",
      "link": "https://robkendal.co.uk",
      "imageUrl": "https://placeimg.com/800/600/nature"
    }
  ]
}
